one_neuron/__init__.py
one_neuron/all_utils.py
one_neuron/perceptron.py
one_neuron_pypi_pralaydas-0.0.5.dist-info/LICENSE
one_neuron_pypi_pralaydas-0.0.5.dist-info/METADATA
one_neuron_pypi_pralaydas-0.0.5.dist-info/WHEEL
one_neuron_pypi_pralaydas-0.0.5.dist-info/top_level.txt
one_neuron_pypi_pralaydas-0.0.5.dist-info/RECORD
