Metadata-Version: 2.1
Name: one-neuron-pypi-pralaydas
Version: 0.0.5
Summary: it is an implementation of perceptron
Home-page: https://github.com/pralaydas/one_neuron_pypi
Author: pralaydas
Author-email: pralay.ceremorphic@gmail.com
License: UNKNOWN
Project-URL: Bug Tracker, https://github.com/pralaydas/one_neuron_pypi/issues
Platform: UNKNOWN
Classifier: Programming Language :: Python :: 3
Classifier: License :: OSI Approved :: MIT License
Classifier: Operating System :: OS Independent
Requires-Python: >=3.7
License-File: LICENSE
Requires-Dist: numpy
